niftiview/__init__.py
niftiview/cli.py
niftiview/config.py
niftiview/core.py
niftiview/data/config.json
niftiview/data/fonts/DejaVuSans.ttf
niftiview/data/glassbrain/brain_schematics_front.svg
niftiview/data/glassbrain/brain_schematics_side.svg
niftiview/data/glassbrain/brain_schematics_top.svg
niftiview/data/glassbrain/lines_axial.npz
niftiview/data/glassbrain/lines_coronal.npz
niftiview/data/glassbrain/lines_sagittal.npz
niftiview/data/glassbrain/svg2npz.py
niftiview/data/niftis/atlases/Schaefer2018_100Parcels_17Networks_order.nii.gz
niftiview/data/niftis/atlases/aal3.nii.gz
niftiview/data/niftis/atlases/aal3.txt
niftiview/data/niftis/atlases/hammers.nii.gz
niftiview/data/niftis/atlases/hammers.txt
niftiview/data/niftis/atlases/ibsr.nii.gz
niftiview/data/niftis/atlases/ibsr.txt
niftiview/data/niftis/atlases/julichbrain.nii.gz
niftiview/data/niftis/atlases/julichbrain.txt
niftiview/data/niftis/atlases/lpba40.nii.gz
niftiview/data/niftis/atlases/lpba40.txt
niftiview/data/niftis/atlases/mori.nii.gz
niftiview/data/niftis/atlases/mori.txt
niftiview/data/niftis/atlases/neuromorphometrics.nii.gz
niftiview/data/niftis/atlases/neuromorphometrics.txt
niftiview/data/niftis/atlases/schaefer.txt
niftiview/data/niftis/atlases/suit.nii.gz
niftiview/data/niftis/atlases/suit.txt
niftiview/data/niftis/templates/T1.nii.gz
niftiview/data/niftis/templates/ch2.nii.gz
niftiview/data/niftis/templates/mni152.nii.gz
niftiview/glass.py
niftiview/grid.py
niftiview/image.py
niftiview/overlay.py
niftiview/utils.py
niftiview-1.1.2.dist-info/LICENSE
niftiview-1.1.2.dist-info/METADATA
niftiview-1.1.2.dist-info/WHEEL
niftiview-1.1.2.dist-info/entry_points.txt
niftiview-1.1.2.dist-info/RECORD
