Metadata-Version: 2.3
Name: niftiview
Version: 1.1.2
Summary: View volumetric images in Python 🧠
License: MIT
Author: codingfisch
Author-email: l_fisc17@wwu.de
Requires-Python: >=3.9,<4.0
Classifier: Intended Audience :: Science/Research
Classifier: License :: OSI Approved :: MIT License
Classifier: Operating System :: OS Independent
Classifier: Programming Language :: Python :: 3
Classifier: Programming Language :: Python :: 3.9
Classifier: Programming Language :: Python :: 3.10
Classifier: Programming Language :: Python :: 3.11
Classifier: Programming Language :: Python :: 3.12
Classifier: Programming Language :: Python :: 3.13
Requires-Dist: affine-image
Requires-Dist: cmap
Requires-Dist: colorbar (>=0.2.0)
Requires-Dist: nibabel
Requires-Dist: pillow
Requires-Dist: tqdm
Project-URL: Repository, https://github.com/codingfisch/niftiview
